Metadata-Version: 2.1
Name: fasta-merge
Version: 0.0.1
Summary: A command line tool to merge multiple alignments to the same sequence
Home-page: https://github.com/kxnr/FASTAMerge
Author: Connor Keane
Author-email: connor.keane@kxnr.me
License: UNKNOWN
Project-URL: Bug Tracker, https://github.com/kxnr/FASTAMerge/issues
Platform: UNKNOWN
Classifier: Programming Language :: Python :: 3 :: Only
Classifier: License :: OSI Approved :: GNU General Public License v3 (GPLv3)
Classifier: Operating System :: OS Independent
Requires-Python: >=3.6
License-File: LICENSE.md
